peapod/__init__.py
peapod/alignment.py
peapod/batchcorrection.py
peapod/benchmark.py
peapod/fft.py
peapod/gaps.py
peapod/methods.py
peapod/mncm.py
peapod/plms.py
peapod/pozitiv.py
peapod/similarity.py
peapod/utilities.py
peapod/visualize.py
peapod/substitutionmatrices/blosum45.tsv
peapod/substitutionmatrices/blosum45.txt
peapod/substitutionmatrices/blosum62.tsv
peapod/substitutionmatrices/blosum62.txt
peapod/substitutionmatrices/blosum80.tsv
peapod/substitutionmatrices/blosum80.txt
peapod-0.1.6.dist-info/METADATA
peapod-0.1.6.dist-info/WHEEL
peapod-0.1.6.dist-info/licenses/LICENSE
peapod-0.1.6.dist-info/RECORD
