Metadata-Version: 2.4
Name: peapod
Version: 0.1.6
Summary: Protein Embedding Aligner Plus Output Display
Project-URL: Homepage, https://github.com/CalvinRusley/peapod
Project-URL: Source Code, https://github.com/CalvinRusley/peapod
Project-URL: Bug Tracker, https://github.com/CalvinRusley/peapod/issues
Project-URL: Documentation, https://peapod.readthedocs.io
Project-URL: Download, https://pypi.org/project/peapod/#files
Author: Calvin Rusley
Maintainer: Calvin Rusley
License-Expression: MIT
License-File: LICENSE
Keywords: aligner,alignment,embedding,plm,protein,sequence
Classifier: Development Status :: 2 - Pre-Alpha
Classifier: Intended Audience :: Science/Research
Classifier: License :: OSI Approved :: MIT License
Classifier: Operating System :: OS Independent
Classifier: Programming Language :: Python :: 3 :: Only
Requires-Python: >=3.9.16
Requires-Dist: ankh==1.10.0
Requires-Dist: bokeh>=3.4.3
Requires-Dist: fair-esm==2.0.0
Requires-Dist: holoviews>=1.20.2
Requires-Dist: inmoosepeapod==0.8.2.dev0
Requires-Dist: numba>=0.60.0
Requires-Dist: numpy>=2.0.2
Requires-Dist: pandas>=2.3.1
Requires-Dist: pyarrow>=17.0.0
Requires-Dist: scipy>=1.13.1
Requires-Dist: sentencepiece>=0.1.99
Requires-Dist: torch>=2.6.0
Requires-Dist: transformers>=4.49.0
Provides-Extra: dev
Requires-Dist: hatch; extra == 'dev'
Requires-Dist: pre-commit; extra == 'dev'
